martextemotiondetection/EmotionDetector.py
martextemotiondetection/__init__.py
martextemotiondetection-0.2.dist-info/METADATA
martextemotiondetection-0.2.dist-info/WHEEL
martextemotiondetection-0.2.dist-info/top_level.txt
martextemotiondetection-0.2.dist-info/RECORD
