Metadata-Version: 2.1
Name: martextemotiondetection
Version: 0.2
Summary: Text Emotion Detection using Machine Learning
Home-page: https://github.com/joemar25/MarTextEmotionDetection
Author: Joemar J.
Author-email: 
License: MIT
Keywords: text emotion detection machine learning
Classifier: Development Status :: 3 - Alpha
Classifier: Intended Audience :: Developers
Classifier: License :: OSI Approved :: MIT License
Classifier: Programming Language :: Python :: 3.10
Requires-Dist: numpy
Requires-Dist: tensorflow
Requires-Dist: transformers
